microservice_request/__init__.py
microservice_request/decorators.py
microservice_request/exceptions.py
microservice_request/middleware.py
microservice_request/permissions.py
microservice_request/services.py
microservice_request/test.py
django_microservice_request-0.5.3.dist-info/LICENSE
django_microservice_request-0.5.3.dist-info/METADATA
django_microservice_request-0.5.3.dist-info/WHEEL
django_microservice_request-0.5.3.dist-info/top_level.txt
django_microservice_request-0.5.3.dist-info/RECORD
